iris_tools/__init__.py
iris_tools/_defs.py
iris_tools/cleanup.py
iris_tools/common.py
iris_tools/molprobity_scrape.py
iris_tools/pdb_redo_scrape.py
iris_tools/percentiles_generate_data.py
iris_tools/percentiles_generate_graphs.py
iris_tools/rama_test.py
iris_tools/reflections_test.py
iris_tools/rotamer_generate_library.py
iris_tools/rotamer_test.py
iris_tools/time_i2.py
iris_tools/time_i2_graphs.py
iris_tools/time_self.py
iris_tools/time_self_graphs.py
iris_validation/__init__.py
iris_validation/_defs.py
iris_validation/utils.py
iris_validation/clipper/__init__.py
iris_validation/interface/__init__.py
iris_validation/interface/charts.py
iris_validation/interface/report.py
iris_validation/interface/svgwrite/__init__.py
iris_validation/interface/svgwrite/animate.py
iris_validation/interface/svgwrite/base.py
iris_validation/interface/svgwrite/container.py
iris_validation/interface/svgwrite/drawing.py
iris_validation/interface/svgwrite/elementfactory.py
iris_validation/interface/svgwrite/etree.py
iris_validation/interface/svgwrite/filters.py
iris_validation/interface/svgwrite/gradients.py
iris_validation/interface/svgwrite/image.py
iris_validation/interface/svgwrite/masking.py
iris_validation/interface/svgwrite/mixins.py
iris_validation/interface/svgwrite/params.py
iris_validation/interface/svgwrite/path.py
iris_validation/interface/svgwrite/pattern.py
iris_validation/interface/svgwrite/shapes.py
iris_validation/interface/svgwrite/solidcolor.py
iris_validation/interface/svgwrite/text.py
iris_validation/interface/svgwrite/utils.py
iris_validation/interface/svgwrite/validator2.py
iris_validation/interface/svgwrite/version.py
iris_validation/interface/svgwrite/data/__init__.py
iris_validation/interface/svgwrite/data/colors.py
iris_validation/interface/svgwrite/data/full11.py
iris_validation/interface/svgwrite/data/pattern.py
iris_validation/interface/svgwrite/data/svgparser.py
iris_validation/interface/svgwrite/data/tiny12.py
iris_validation-0.0.0.dist-info/LICENSE
iris_validation-0.0.0.dist-info/METADATA
iris_validation-0.0.0.dist-info/WHEEL
iris_validation-0.0.0.dist-info/top_level.txt
iris_validation-0.0.0.dist-info/RECORD
