Metadata-Version: 2.1
Name: iris-validation
Version: 0.0.0
Summary: A package for interactive all-in-one graphical validation of 3D protein model iterations
Home-page: https://github.com/wrochira/iris-validation
Author: William Rochira
Author-email: william.rochira@hotmail.co.uk
License: UNKNOWN
Platform: UNKNOWN
Classifier: Programming Language :: Python :: 2.7
Classifier: License :: OSI Approved :: MIT License
Classifier: Operating System :: OS Independent
Requires-Python: >=2.7, <3
